horse_race_simulator/runs.csv
horse_race_simulator/race_data/horse_stats.py
horse_race_simulator/race_data/race_details.py
horse_race_simulator/race_data/track_data.py
horse_race_simulator/simulation/betting.py
horse_race_simulator/simulation/race_results.py
horse_race_simulator/simulation/race_simulator.py
Horsim-0.0.4.dist-info/LICENSE.txt
Horsim-0.0.4.dist-info/METADATA
Horsim-0.0.4.dist-info/WHEEL
Horsim-0.0.4.dist-info/top_level.txt
Horsim-0.0.4.dist-info/RECORD
