Metadata-Version: 2.1
Name: Horsim
Version: 0.0.4
Summary: Horsim package
Author-email: Amali <amali.jayatileke14@gmail.com>
Project-URL: Homepage, https://github.com/JKiran4/Horse-Race-Simulator
Classifier: Programming Language :: Python :: 3
Classifier: License :: OSI Approved :: MIT License
Classifier: Operating System :: OS Independent
Requires-Python: >=3.8
License-File: LICENSE.txt
